fastapi_authenticator/__init__.py
fastapi_authenticator-0.1.1.dist-info/LICENSE
fastapi_authenticator-0.1.1.dist-info/METADATA
fastapi_authenticator-0.1.1.dist-info/WHEEL
fastapi_authenticator-0.1.1.dist-info/top_level.txt
fastapi_authenticator-0.1.1.dist-info/RECORD
