Metadata-Version: 2.1
Name: fastapi-authenticator
Version: 0.1.1
Summary: fastapi authenticator for google cloud tasks
Home-page: https://github.com/guyingbo/fastapi-authenticator
Author: Yingbo Gu
Author-email: tensiongyb@gmail.com
Maintainer: Yingbo Gu
Maintainer-email: tensiongyb@gmail.com
License: MIT
Platform: UNKNOWN
Classifier: License :: OSI Approved :: MIT License
Classifier: Intended Audience :: Developers
Classifier: Programming Language :: Python :: 3.6
Classifier: Programming Language :: Python :: 3.7
Classifier: Programming Language :: Python :: 3.8
Requires-Python: >=3.6
Requires-Dist: httpx
Requires-Dist: fastapi
Requires-Dist: python-jose
